Workbook

Sheet Instructions
A1: Foodluk white-box manual test workbook
A3: Field | B3: Instructions
A4: How to mark results | B4: On Users & RBAC or Full system: pick Result (Not Run / Pass / Fail / Blocked). Then tick Approved (☑) or Rejected (☑) using the dropdown. Do not tick both.
A5: Approved | B5: Use only when Result = Pass. Green cell when ☑.
A6: Rejected | B6: Use only when Result = Fail or the case is invalid. Red cell when ☑.
A7: Filter | B7: Row 1 is frozen with AutoFilter. Filter by Area, Result, Approved, or Rejected.
A8: Actors to prepare | B8: Owner (GROWTH), Owner (STARTER), Admin employee, Cashier (pos+sales), Kitchen (kds), Settings access-only, Settings edit-only, empty-permission user, platform admin, customer account, second restaurant.
A9: RBAC tokens | B9: Each dashboard module has access / edit / delete. Delete implies edit implies access. Account owner always has full access.
A10: Sheets | B10: Users & RBAC = team, invites, roles, permissions, plan gates. Full system = marketing through POS, kiosk, storefront, payments, catalog, admin, E2E, security.
A11: Summary | B11: Counts update automatically from Result / Approved / Rejected columns.

Sheet Users & RBAC
A1: ID | B1: Area | C1: Title | D1: Actor | E1: Preconditions | F1: Steps | G1: Expected | H1: White-box / API | I1: Result | J1: Approved | K1: Rejected | L1: Notes | M1: Tester | N1: Tested on
A2: USR-01 | B2: Staff login | C2: Owner email login | D2: Owner | E2: GROWTH restaurant exists | F2: Login with owner email/password | G2: Dashboard loads; all nav items visible | H2: JWT + Employee Owner role | I2: Not Run | J2: ☐ | K2: ☐
A3: USR-02 | B3: Staff login | C3: Wrong password | D3: Anyone | E3: Valid email | F3: Submit wrong password | G3: Stay on /login; no session | H3: authorize returns null | I3: Not Run | J3: ☐ | K3: ☐
A4: USR-03 | B4: Staff login | C4: Employee limited login | D4: Cashier | E4: Custom pos+sales role | F4: Login as cashier | G4: Only POS/Sales in sidebar | H4: navItemsForPermissions | I4: Not Run | J4: ☐ | K4: ☐
A5: USR-04 | B5: Staff login | C5: Customer cannot use dashboard | D5: Customer | E5: CustomerAccount only | F5: Open /login then /dashboard | G5: No restaurant dashboard (unless they also have a staff User) | H5: CustomerAccount ≠ staff User | I5: Not Run | J5: ☐ | K5: ☐
A6: USR-05 | B6: Staff signup | C6: Google new worker | D6: New Google user | E6: Google OAuth on | F6: Sign up as worker | G6: Global pending_worker; no restaurant until invite | H6: GLOBAL_ROLE_SLUG.PENDING_WORKER | I6: Not Run | J6: ☐ | K6: ☐
A7: USR-06 | B7: Staff signup | C7: Google new owner | D7: New Google user | E7: Google OAuth on | F7: Sign up as OWNER then onboard | G7: pending_owner then restaurant created | H7: /role + onboarding | I7: Not Run | J7: ☐ | K7: ☐
A8: USR-07 | B8: Staff users | C8: New employee weak password | D8: Owner | E8: settings:edit | F8: Create user with 7-char password | G8: 400; password must be ≥ 8 | H8: isStrongPassword | I8: Not Run | J8: ☐ | K8: ☐
A9: USR-08 | B9: Staff users | C9: Duplicate staff on same restaurant | D9: Owner | E9: User already employee | F9: Invite same email again | G9: 409 already part of this restaurant | H9: unique userId_restaurantId | I9: Not Run | J9: ☐ | K9: ☐
A10: USR-09 | B10: Staff login | C10: Logout then protected route | D10: Staff | E10: Logged in | F10: Logout; open /pos | G10: Redirect /login?callbackUrl= | H10: middleware needsAuth | I10: Not Run | J10: ☐ | K10: ☐
A11: USR-10 | B11: Staff login | C11: Empty permissions account | D11: Empty-role employee | E11: Custom role with no tokens | F11: Login | G11: Message: no dashboard permissions returned | H11: (root)/layout permissions.length === 0 | I11: Not Run | J11: ☐ | K11: ☐
A12: USR-11 | B12: Platform admin | C12: Admin can open /admin | D12: Platform admin | E12: Email in ADMIN_EMAIL(S) | F12: Open /admin/dashboard | G12: Admin console loads | H12: isPlatformAdmin | I12: Not Run | J12: ☐ | K12: ☐
A13: USR-12 | B13: Platform admin | C13: Restaurant owner blocked from /admin | D13: Owner | E13: Not in ADMIN_EMAILS | F13: Open /admin/dashboard | G13: Redirect to / | H13: middleware admin gate | I13: Not Run | J13: ☐ | K13: ☐
... A105: PLAN-07 | B105: Plan gating | C105: Upgrade GROWTH unlocks roles | D105: Former STARTER | E105: Upgraded | F105: Create Cashier + invite | G105: Works | H105: roleBasedSettings true | I105: Not Run | J105: ☐ | K105: ☐
A106: PLAN-08 | B106: Plan gating | C106: Downgrade STARTER leftover cashiers | D106: GROWTH→STARTER | E106: Cashiers exist | F106: Cashiers still login; Access UI hidden; cannot create new customs | G106: Leftover employees keep tokens | I106: Not Run | J106: ☐ | K106: ☐
A107: OWN-01 | B107: Owner vs Admin | C107: Account owner always full | D107: Owner | E107: Even if role tokens stale | F107: Use all modules | G107: All allowed | H107: ownerId short-circuit | I107: Not Run | J107: ☐ | K107: ☐
A108: OWN-02 | B108: Owner vs Admin | C108: Preset Admin is full via role rows | D108: Admin employee | E108: Not ownerId | F108: Use all modules | G108: Full nav | H108: seeded full permissions | I108: Not Run | J108: ☐ | K108: ☐
A109: OWN-03 | B109: Owner vs Admin | C109: Strip Admin role in DB | D109: Admin | E109: Permissions emptied | F109: Refresh | G109: Admin loses modules (unlike owner) | H109: uses role.permissions | I109: Not Run | J109: ☐ | K109: ☐
A110: OWN-04 | B110: Owner vs Admin | C110: Admin cannot remove owner | D110: Admin | E110: settings:delete | F110: DELETE owner | G110: 403 | H110: owner guard | I110: Not Run | J110: ☐ | K110: ☐
A111: OWN-05 | B111: Owner vs Admin | C111: Admin can invite/remove cashiers | D111: Admin | E111: Preset Admin | F111: Invite and remove cashier | G111: Succeeds | H111: full settings tokens | I111: Not Run | J111: ☐ | K111: ☐
A112: OWN-06 | B112: Owner vs Admin | C112: Admin can switch all branches | D112: Admin | E112: 2+ branches | F112: Switcher in header | G112: All branches listed | H112: userIsOwnerOrAdmin | I112: Not Run | J112: ☐ | K112: ☐
A113: OWN-07 | B113: Owner vs Admin | C113: Almost-admin without settings | D113: Custom full except settings | E113: No settings:* | F113: Open Access UI | G113: /settings → no-access | H113: RBAC | I113: Not Run | J113: ☐ | K113: ☐
A114: CUS-01 | B114: Customer users | C114: Register on storefront | D114: Guest | E114: Restaurant slug | F114: Register email/password | G114: CustomerAccount created for that restaurant | H114: unique restaurantId+emailNormalized | I114: Not Run | J114: ☐ | K114: ☐
A115: CUS-02 | B115: Customer users | C115: Same email two restaurants | D115: Guest | E115: Two restaurants | F115: Register same email on both | G115: Two separate accounts | H115: composite unique | I115: Not Run | J115: ☐ | K115: ☐
A116: CUS-03 | B116: Customer users | C116: Customer Google login | D116: Guest | E116: Google customer OAuth | F116: Login on storefront | G116: customer-auth/google; not staff dashboard | H116: middleware rewrite callback | I116: Not Run | J116: ☐ | K116: ☐
A117: CUS-04 | B117: Customer users | C117: Customer opens /dashboard | D117: Customer | E117: No staff User | F117: Open /dashboard | G117: Redirect /login | H117: middleware | I117: Not Run | J117: ☐ | K117: ☐
A118: CUS-05 | B118: Customer users | C118: Disabled customer | D118: Customer | E118: disabledAt set | F118: Login | G118: Login fails | H118: disabledAt | I118: Not Run | J118: ☐ | K118: ☐
A119: CUS-06 | B119: Customer users | C119: Guest vs logged-in order owner | D119: Guest then customer | E119: Place both orders | F119: Guest customerAccountId null; logged-in set | G119: Order model | H119: Order.customerAccountId | I119: Not Run | J119: ☐ | K119: ☐
A120: CUS-07 | B120: Customer users | C120: Customer cannot list employees | D120: Customer session | E120: Call GET /api/restaurant/employees | F120: 401/403 | G120: staff session required | I120: Not Run | J120: ☐ | K120: ☐
A121: SEC-U-01 | B121: Security | C121: Unauthenticated GET employees | D121: Guest | E121: — | F121: GET /api/restaurant/employees | G121: 401 | H121: require session | I121: Not Run | J121: ☐ | K121: ☐
A122: SEC-U-02 | B122: Security | C122: Cannot list other restaurant team | D122: Owner A | E122: Restaurant B exists | F122: GET employees | G122: Only restaurant A rows | H122: getRestaurantIdForRequest | I122: Not Run | J122: ☐ | K122: ☐
A123: SEC-U-03 | B123: Security | C123: Forge other restaurant roleId on invite | D123: Owner A | E123: roleId from B | F123: POST invite | G123: 400 Role not found for this restaurant | H123: assertAssignableRestaurantRole | I123: Not Run | J123: ☐ | K123: ☐
A124: SEC-U-04 | B124: Security | C124: Forge other restaurant branchIds | D124: Owner A | E124: branchId from B | F124: Invite/PATCH branches | G124: Only valid restaurant branches saved | H124: syncEmployeeBranches filters | I124: Not Run | J124: ☐ | K124: ☐
A125: SEC-U-05 | B125: Security | C125: Accept someone else invite token | D125: Other user | E125: Valid token for other email | F125: POST accept | G125: 403 wrong email | H125: email match | I125: Not Run | J125: ☐ | K125: ☐
A126: SEC-U-06 | B126: Security | C126: Staff session ≠ customer session | D126: Both accounts | E126: Same browser | F126: Logout staff; customer cookie remains independent | G126: Separate cookies | H126: NextAuth vs CustomerSession | I126: Not Run | J126: ☐ | K126: ☐

Sheet Full system
A1: ID | B1: Area | C1: Title | D1: Actor | E1: Preconditions | F1: Steps | G1: Expected | H1: White-box / API | I1: Result | J1: Approved | K1: Rejected | L1: Notes | M1: Tester | N1: Tested on
A2: XC-01 | B2: Cross-cutting | C2: Unauthenticated dashboard | D2: Guest | E2: — | F2: Open /dashboard /pos /admin | G2: Redirect /login?callbackUrl= | H2: middleware needsAuth | I2: Not Run | J2: ☐ | K2: ☐
A3: XC-02 | B3: Cross-cutting | C3: Non-admin hits admin | D3: Owner | E3: — | F3: Open /admin/dashboard | G3: Redirect / | H3: isPlatformAdmin | I3: Not Run | J3: ☐ | K3: ☐
A4: XC-03 | B4: Cross-cutting | C4: Missing module permission | D4: Employee | E4: No product:access | F4: Open /product | G4: /no-access or API Access Blocked | H4: permissionName | I4: Not Run | J4: ☐ | K4: ☐
A5: XC-04 | B5: Cross-cutting | C5: Delete implies edit+access | D5: Custom role | E5: product:delete only | F5: Use product module | G5: Can view edit delete | H5: normalizeDashboardPermissions | I5: Not Run | J5: ☐ | K5: ☐
A6: XC-05 | B6: Cross-cutting | C6: Edit implies access | D6: Custom role | E6: product:edit only | F6: Use product module | G6: View+edit; cannot delete | H6: same | I6: Not Run | J6: ☐ | K6: ☐
A7: XC-06 | B7: Cross-cutting | C7: Access only | D7: Custom role | E7: product:access only | F7: Create/update/delete | G7: Writes 403 | H7: action edit/delete | I7: Not Run | J7: ☐ | K7: ☐
A8: XC-07 | B8: Cross-cutting | C8: Tenant isolation | D8: Owner A | E8: Restaurant B ids | F8: Hit B resource ids | G8: 404 / Access Blocked | H8: getRestaurantForUser | I8: Not Run | J8: ☐ | K8: ☐
A9: XC-08 | B9: Cross-cutting | C9: Branch cookie scope | D9: Cashier | E9: Assigned Branch 1 | F9: Switch/forge other branch | G9: Other branches hidden; orders scoped | H9: /api/me/active-branch EmployeeBranch | I9: Not Run | J9: ☐ | K9: ☐
A10: XC-09 | B10: Cross-cutting | C10: Subscription expired | D10: Expired owner | E10: Trial/period ended | F10: Open dashboard | G10: Blocked / pricing | H10: evaluateSubscriptionAccess | I10: Not Run | J10: ☐ | K10: ☐
A11: XC-10 | B11: Cross-cutting | C11: Plan feature denied | D11: STARTER | E11: STARTER | F11: Save logo or recommendation | G11: 403 plan-denied | H11: subscriptionPlanDeniedResponse | I11: Not Run | J11: ☐ | K11: ☐
A12: XC-11 | B12: Cross-cutting | C12: SSE live updates | D12: POS+KDS users | E12: Two browsers | F12: Place POS order | G12: KDS updates without refresh | H12: /api/restaurant/realtime/stream | I12: Not Run | J12: ☐ | K12: ☐
A13: XC-12 | B13: Cross-cutting | C13: Legacy storefront URL | D13: Guest | E13: — | F13: Open /web-app/{slug} | G13: 308 redirect | H13: legacyWebAppRedirectPath | I13: Not Run | J13: ☐ | K13: ☐
... A255: SEC-09 | B255: Security | C255: Webhook invalid signature | D255: Attacker | E255: — | F255: POST webhook | G255: 400 order unchanged | H255: signature check | I255: Not Run | J255: ☐ | K255: ☐

Sheet Summary
A1: Test progress
A3: Metric | B3: Users & RBAC | C3: Full system | D3: Total
A4: Total cases | B4: =COUNTA('Users & RBAC'!A2:A126) | C4: =COUNTA('Full system'!A2:A255) | D4: =B4+C4
A5: Not Run | B5: =COUNTIF('Users & RBAC'!I:I,"Not Run") | C5: =COUNTIF('Full system'!I:I,"Not Run") | D5: =B5+C5
A6: Pass | B6: =COUNTIF('Users & RBAC'!I:I,"Pass") | C6: =COUNTIF('Full system'!I:I,"Pass") | D6: =B6+C6
A7: Fail | B7: =COUNTIF('Users & RBAC'!I:I,"Fail") | C7: =COUNTIF('Full system'!I:I,"Fail") | D7: =B7+C7
A8: Blocked | B8: =COUNTIF('Users & RBAC'!I:I,"Blocked") | C8: =COUNTIF('Full system'!I:I,"Blocked") | D8: =B8+C8
A9: Approved (☑) | B9: =COUNTIF('Users & RBAC'!J:J,"☑") | C9: =COUNTIF('Full system'!J:J,"☑") | D9: =B9+C9
A10: Rejected (☑) | B10: =COUNTIF('Users & RBAC'!K:K,"☑") | C10: =COUNTIF('Full system'!K:K,"☑") | D10: =B10+C10
A12: Tip: filter Result = Fail on a case sheet, then tick Rejected. Filter Result = Pass, then tick Approved.
