Workbook

Sheet Instructions
A1: Foodluk full-system test workbook
A3: Topic | B3: Instructions
A4: How to mark | B4: Set Result (Not Run / Pass / Fail / Blocked). Tick Approved ☑ only for Pass. Tick Rejected ☑ only for Fail. Never both.
A5: Modules | B5: Each dashboard module: load, sidebar, no-access, access-only, edit, delete. Plus analytics, admin, storefront, kiosk, marketing.
A6: Functionality | B6: Business rules: auth, subscription caps, POS/KDS/kiosk/storefront/payments/catalog/inventory math and flows.
A7: RBAC | B7: Owner vs Admin vs custom roles, invites, branches, plan gating, customer vs staff.
A8: Security | B8: Authn/authz, tenant isolation, IDOR, webhooks, XSS, uploads, middleware.
A9: API | B9: One happy-path case per endpoint (method + path) plus shared negatives (401/403/400/plan).
A10: UI | B10: Every major page load plus cross-UI (mobile, empty, wizard, toasts, theme).
A11: Full system | B11: End-to-end journeys across modules (highest priority after smoke).
A12: Actors | B12: Owner GROWTH, Owner STARTER, Admin, Cashier, Kitchen, Viewer, Settings access/edit, empty role, platform admin, customer, second restaurant, guest.
A13: Counts | B13: Modules: 99 | Functionality: 87 | RBAC: 47 | Security: 32 | API: 201 | UI: 108 | Full system: 25

Sheet 01-Modules
A1: ID | B1: Area | C1: Title | D1: Actor | E1: Preconditions | F1: Steps | G1: Expected | H1: White-box / API | I1: Result | J1: Approved | K1: Rejected | L1: Notes | M1: Tester | N1: Tested on
A2: MOD-dashboard-01 | B2: Dashboard | C2: Dashboard page loads | D2: Owner | E2: dashboard:access; GROWTH if needed | F2: Open /dashboard | G2: Page renders; no crash; main content visible | H2: /dashboard | I2: Not Run | J2: ☐ | K2: ☐
A3: MOD-dashboard-02 | B3: Dashboard | C3: Dashboard in sidebar | D3: Owner | E3: Logged in | F3: View dashboard sidebar | G3: Dashboard link shown and active on /dashboard | H3: navItemsForPermissions | I3: Not Run | J3: ☐ | K3: ☐
A4: MOD-dashboard-03 | B4: Dashboard | C4: Dashboard blocked without permission | D4: Limited employee | E4: No dashboard:* tokens | F4: Open /dashboard directly | G4: Dashboard exception: not redirected (confirm widgets) | H4: layout allowedModuleKeys | I4: Not Run | J4: ☐ | K4: ☐
A5: MOD-dashboard-04 | B5: Dashboard | C5: Dashboard hidden in nav without permission | D5: Limited employee | E5: No dashboard:* | F5: View sidebar | G5: Dashboard not listed | H5: canAccessDashboardModule | I5: Not Run | J5: ☐ | K5: ☐
A6: MOD-sales-01 | B6: Sales | C6: Sales page loads | D6: Owner | E6: sales:access; GROWTH if needed | F6: Open /sales | G6: Page renders; no crash; main content visible | H6: /sales | I6: Not Run | J6: ☐ | K6: ☐
A7: MOD-sales-02 | B7: Sales | C7: Sales in sidebar | D7: Owner | E7: Logged in | F7: View dashboard sidebar | G7: Sales link shown and active on /sales | H7: navItemsForPermissions | I7: Not Run | J7: ☐ | K7: ☐
A8: MOD-sales-03 | B8: Sales | C8: Sales blocked without permission | D8: Limited employee | E8: No sales:* tokens | F8: Open /sales directly | G8: Redirect /no-access | H8: layout allowedModuleKeys | I8: Not Run | J8: ☐ | K8: ☐
A9: MOD-sales-04 | B9: Sales | C9: Sales hidden in nav without permission | D9: Limited employee | E9: No sales:* | F9: View sidebar | G9: Sales not listed | H9: canAccessDashboardModule | I9: Not Run | J9: ☐ | K9: ☐
A10: MOD-pos-01 | B10: POS | C10: POS page loads | D10: Owner | E10: pos:access; GROWTH if needed | F10: Open /pos | G10: Page renders; no crash; main content visible | H10: /pos | I10: Not Run | J10: ☐ | K10: ☐
A11: MOD-pos-02 | B11: POS | C11: POS in sidebar | D11: Owner | E11: Logged in | F11: View dashboard sidebar | G11: POS link shown and active on /pos | H11: navItemsForPermissions | I11: Not Run | J11: ☐ | K11: ☐
A12: MOD-pos-03 | B12: POS | C12: POS blocked without permission | D12: Limited employee | E12: No pos:* tokens | F12: Open /pos directly | G12: Redirect /no-access | H12: layout allowedModuleKeys | I12: Not Run | J12: ☐ | K12: ☐
A13: MOD-pos-04 | B13: POS | C13: POS hidden in nav without permission | D13: Limited employee | E13: No pos:* | F13: View sidebar | G13: POS not listed | H13: canAccessDashboardModule | I13: Not Run | J13: ☐ | K13: ☐
... A100: MOD-MKT-01 | B100: Marketing | C100: Public SaaS marketing | D100: Guest | E100: — | F100: Open / pricing blog docs | G100: Public pages load | H100: (saas) routes | I100: Not Run | J100: ☐ | K100: ☐

Sheet 02-Functionality
A1: ID | B1: Area | C1: Title | D1: Actor | E1: Preconditions | F1: Steps | G1: Expected | H1: White-box / API | I1: Result | J1: Approved | K1: Rejected | L1: Notes | M1: Tester | N1: Tested on
A2: FN-AUTH-01 | B2: Auth | C2: Email login success | D2: Staff | E2: Password ≥ 8 | F2: Login | G2: Session + dashboard | H2: POST credentials NextAuth | I2: Not Run | J2: ☐ | K2: ☐
A3: FN-AUTH-02 | B3: Auth | C3: Register owner then onboard 1–3 | D3: New owner | E3: — | F3: Register OWNER; steps 1–3 | G3: Restaurant + trial + dashboard | H3: /api/onboarding/step1-3 | I3: Not Run | J3: ☐ | K3: ☐
A4: FN-AUTH-03 | B4: Auth | C4: Duplicate slug rejected | D4: Pending owner | E4: Taken slug | F4: Step 1 | G4: Unique error | H4: Restaurant.slug | I4: Not Run | J4: ☐ | K4: ☐
A5: FN-AUTH-04 | B5: Auth | C5: Google signup role picker | D5: Google UNKNOW | E5: — | F5: /role OWNER or WORKER | G5: Role saved | H5: POST /api/auth/role | I5: Not Run | J5: ☐ | K5: ☐
A6: FN-AUTH-05 | B6: Auth | C6: Reset password flow | D6: Staff | E6: — | F6: Request + confirm | G6: Can login with new password; expired token fails | H6: /api/auth/reset | I6: Not Run | J6: ☐ | K6: ☐
A7: FN-SUB-01 | B7: Subscription | C7: Trial allows dashboard | D7: Owner | E7: TRIAL future | F7: Open dashboard | G7: Allowed; warning ≤3 days | H7: evaluateSubscriptionAccess | I7: Not Run | J7: ☐ | K7: ☐
A8: FN-SUB-02 | B8: Subscription | C8: Expired trial blocks | D8: Owner | E8: trial ended | F8: Open dashboard | G8: Redirect /pricing | H8: trial_expired | I8: Not Run | J8: ☐ | K8: ☐
A9: FN-SUB-03 | B9: Subscription | C9: STARTER 1 branch cap | D9: STARTER | E9: 1 branch | F9: Add second | G9: 403 | H9: maxBranches 1 | I9: Not Run | J9: ☐ | K9: ☐
A10: FN-SUB-04 | B10: Subscription | C10: GROWTH 5 branch cap | D10: GROWTH | E10: 5 branches | F10: Add sixth | G10: 403 | H10: maxBranches 5 | I10: Not Run | J10: ☐ | K10: ☐
A11: FN-SUB-05 | B11: Subscription | C11: SCALE unlimited branches | D11: SCALE | E11: — | F11: Add many | G11: OK | H11: Infinity | I11: Not Run | J11: ☐ | K11: ☐
A12: FN-SUB-06 | B12: Subscription | C12: STARTER branding denied | D12: STARTER | E12: — | F12: Save logo/theme | G12: 403 | H12: branding false | I12: Not Run | J12: ☐ | K12: ☐
A13: FN-SUB-07 | B13: Subscription | C13: Auto-renew on/off | D13: Owner | E13: PayPal billing | F13: Toggle auto-renew | G13: Message + period behavior | H13: PATCH billing/auto-renew | I13: Not Run | J13: ☐ | K13: ☐
... A88: FN-MKT-02 | B88: Marketing | C88: Demo request appears in admin | D88: Guest then admin | E88: — | F88: Submit demo; open /admin/requests | G88: Lead listed | H88: POST demo-request | I88: Not Run | J88: ☐ | K88: ☐

Sheet 03-RBAC
A1: ID | B1: Area | C1: Title | D1: Actor | E1: Preconditions | F1: Steps | G1: Expected | H1: White-box / API | I1: Result | J1: Approved | K1: Rejected | L1: Notes | M1: Tester | N1: Tested on
A2: RBAC-OWN-01 | B2: Owner | C2: Account owner always full modules | D2: Owner | E2: Even if role tokens emptied | F2: Open all modules | G2: All allowed | H2: ownerId short-circuit | I2: Not Run | J2: ☐ | K2: ☐
A3: RBAC-OWN-02 | B3: Owner | C3: Cannot demote owner | D3: Admin | E3: Owner employee | F3: PATCH off Owner role | G3: 403 must stay Owner | H3: employees PATCH | I3: Not Run | J3: ☐ | K3: ☐
A4: RBAC-OWN-03 | B4: Owner | C4: Cannot remove owner | D4: Admin | E4: — | F4: DELETE owner | G4: 403 | H4: employees DELETE | I4: Not Run | J4: ☐ | K4: ☐
A5: RBAC-OWN-04 | B5: Owner | C5: Cannot invite Owner role | D5: Owner | E5: — | F5: Invite with Owner roleId | G5: 400 | H5: assertAssignableRestaurantRole | I5: Not Run | J5: ☐ | K5: ☐
A6: RBAC-ADM-01 | B6: Admin preset | C6: Admin has all module tokens | D6: Admin employee | E6: Not ownerId | F6: Open all pages | G6: Full nav | H6: seeded full permissions | I6: Not Run | J6: ☐ | K6: ☐
A7: RBAC-ADM-02 | B7: Admin preset | C7: Stripped Admin role loses access | D7: Admin | E7: Permissions emptied in DB | F7: Refresh | G7: Modules gone (unlike owner) | H7: role.permissions | I7: Not Run | J7: ☐ | K7: ☐
A8: RBAC-ADM-03 | B8: Admin preset | C8: Admin can switch all branches | D8: Admin | E8: 2+ branches | F8: Header switcher | G8: All branches | H8: userIsOwnerOrAdmin | I8: Not Run | J8: ☐ | K8: ☐
A9: RBAC-IMP-01 | B9: Implications | C9: delete implies edit+access | D9: Custom | E9: product:delete only | F9: View edit delete product | G9: All work | H9: normalizeDashboardPermissions | I9: Not Run | J9: ☐ | K9: ☐
A10: RBAC-IMP-02 | B10: Implications | C10: edit implies access | D10: Custom | E10: product:edit only | F10: Open /product | G10: Page opens; cannot delete | H10: toggleModuleAction | I10: Not Run | J10: ☐ | K10: ☐
A11: RBAC-IMP-03 | B11: Implications | C11: access off clears edit+delete | D11: Owner | E11: GROWTH | F11: Disable product:access | G11: edit+delete cleared | H11: toggleModuleAction | I11: Not Run | J11: ☐ | K11: ☐
A12: RBAC-IMP-04 | B12: Implications | C12: legacy orders:* opens Sales | D12: Cashier | E12: orders:access only | F12: Open /sales | G12: Allowed | H12: SALES_MODULE_ALIASES | I12: Not Run | J12: ☐ | K12: ☐
A13: RBAC-NAV-01 | B13: Nav | C13: Sidebar matches tokens | D13: Cashier | E13: pos+sales only | F13: View sidebar | G13: Only those items (+ dashboard exception) | H13: navItemsForPermissions | I13: Not Run | J13: ☐ | K13: ☐
... A48: RBAC-CUS-02 | B48: Customer | C48: Customer cannot list employees | D48: Customer session | E48: — | F48: GET /api/restaurant/employees | G48: 401/403 | H48: staff session | I48: Not Run | J48: ☐ | K48: ☐

Sheet 04-Security
A1: ID | B1: Area | C1: Title | D1: Actor | E1: Preconditions | F1: Steps | G1: Expected | H1: White-box / API | I1: Result | J1: Approved | K1: Rejected | L1: Notes | M1: Tester | N1: Tested on
A2: SEC-AUTH-01 | B2: Authn | C2: Protected routes redirect login | D2: Guest | E2: — | F2: Open /dashboard /pos /kds /order-display /admin | G2: Redirect /login?callbackUrl= | H2: middleware needsAuth | I2: Not Run | J2: ☐ | K2: ☐
A3: SEC-AUTH-02 | B3: Authn | C3: Staff API without cookie 401 | D3: Guest | E3: — | F3: GET /api/restaurant/menu/products | G3: 401 | H3: requireRestaurantSession | I3: Not Run | J3: ☐ | K3: ☐
A4: SEC-AUTH-03 | B4: Authn | C4: Wrong password no session | D4: Anyone | E4: Valid email | F4: Login bad password | G4: Stay on login | H4: authorize null | I4: Not Run | J4: ☐ | K4: ☐
A5: SEC-AUTH-04 | B5: Authn | C5: Unknown email no enumeration | D5: Guest | E5: — | F5: Login unknown | G5: Same generic fail | H5: no user leak | I5: Not Run | J5: ☐ | K5: ☐
A6: SEC-AUTH-05 | B6: Authn | C6: Password min 8 | D6: Owner | E6: New employee | F6: Password 7 chars | G6: 400 | H6: isStrongPassword | I6: Not Run | J6: ☐ | K6: ☐
A7: SEC-AUTH-06 | B7: Authn | C7: Customer session hashed not raw | D7: Customer | E7: Logged in | F7: Inspect DB CustomerSession | G7: tokenHash SHA-256 only | H7: CustomerSession.tokenHash | I7: Not Run | J7: ☐ | K7: ☐
A8: SEC-AUTHZ-01 | B8: Authz | C8: Forge other restaurant itemId | D8: Owner A | E8: B itemId | F8: GET/PATCH item | G8: 404 no leak | H8: restaurantId scope | I8: Not Run | J8: ☐ | K8: ☐
A9: SEC-AUTHZ-02 | B9: Authz | C9: Forge other restaurant employeeId | D9: Owner A | E9: B employee | F9: DELETE | G9: 404 | H9: scoped findFirst | I9: Not Run | J9: ☐ | K9: ☐
A10: SEC-AUTHZ-03 | B10: Authz | C10: Forge roleId from other restaurant | D10: Owner A | E10: B roleId | F10: Invite | G10: 400 Role not found for this restaurant | H10: assertAssignableRestaurantRole | I10: Not Run | J10: ☐ | K10: ☐
A11: SEC-AUTHZ-04 | B11: Authz | C11: Forge branchIds from other restaurant | D11: Owner A | E11: B branchId | F11: PATCH branches | G11: Ignored; only valid ids saved | H11: syncEmployeeBranches | I11: Not Run | J11: ☐ | K11: ☐
A12: SEC-AUTHZ-05 | B12: Authz | C12: Customer APIs resolve slug/host not staff restaurant | D12: Staff+guest | E12: — | F12: Call customer menu with other slug | G12: Other tenant menu or 404 | H12: customer restaurant route | I12: Not Run | J12: ☐ | K12: ☐
A13: SEC-AUTHZ-06 | B13: Authz | C13: Admin API as restaurant owner 403 | D13: Owner | E13: — | F13: GET /api/admin/overview | G13: 403 Access Blocked | H13: adminRequest.ts | I13: Not Run | J13: ☐ | K13: ☐
... A33: SEC-IDOR-02 | B33: IDOR | C33: Customer me/orders other id | D33: Customer A | E33: B orderId | F33: GET me/orders/[id] | G33: 404 | H33: account scoped | I33: Not Run | J33: ☐ | K33: ☐

Sheet 05-API
A1: ID | B1: Area | C1: Title | D1: Actor | E1: Preconditions | F1: Steps | G1: Expected | H1: White-box / API | I1: Result | J1: Approved | K1: Rejected | L1: Notes | M1: Tester | N1: Tested on
A2: API-001 | B2: Me | C2: GET Bootstrap permissions branches subscription | D2: staff | E2: Auth = staff | F2: GET /api/me/bootstrap with valid payload | G2: 200 payload | H2: GET /api/me/bootstrap | I2: Not Run | J2: ☐ | K2: ☐
A3: API-002 | B3: Me | C3: GET Dashboard permission tokens | D3: staff | E3: Auth = staff | F3: GET /api/me/dashboard-permissions with valid payload | G3: 200 string[] | H3: GET /api/me/dashboard-permissions | I3: Not Run | J3: ☐ | K3: ☐
A4: API-003 | B4: Me | C4: GET Subscription access evaluation | D4: staff | E4: Auth = staff | F4: GET /api/me/subscription-access with valid payload | G4: 200 allowed/reason | H4: GET /api/me/subscription-access | I4: Not Run | J4: ☐ | K4: ☐
A5: API-004 | B5: Me | C5: GET Branch scope | D5: staff | E5: Auth = staff | F5: GET /api/me/branch-context with valid payload | G5: 200 allowedBranchIds | H5: GET /api/me/branch-context | I5: Not Run | J5: ☐ | K5: ☐
A6: API-005 | B6: Me | C6: POST Set active branch cookie | D6: staff | E6: Auth = staff | F6: POST /api/me/active-branch with valid payload | G6: 200 owner/admin only switch | H6: POST /api/me/active-branch | I6: Not Run | J6: ☐ | K6: ☐
A7: API-006 | B7: Restaurant | C7: GET Get restaurant profile | D7: staff | E7: Auth = staff | F7: GET /api/restaurant with valid payload | G7: 200 | H7: GET /api/restaurant | I7: Not Run | J7: ☐ | K7: ☐
A8: API-007 | B8: Restaurant | C8: PATCH Update restaurant / branding | D8: settings:edit | E8: Auth = settings:edit | F8: PATCH /api/restaurant with valid payload | G8: 200 or plan 403 | H8: PATCH /api/restaurant | I8: Not Run | J8: ☐ | K8: ☐
A9: API-008 | B9: Restaurant | C9: GET Get currency country | D9: staff | E9: Auth = staff | F9: GET /api/restaurant/regional with valid payload | G9: 200 | H9: GET /api/restaurant/regional | I9: Not Run | J9: ☐ | K9: ☐
A10: API-009 | B10: Restaurant | C10: PATCH Patch currency country | D10: settings:edit | E10: Auth = settings:edit | F10: PATCH /api/restaurant/regional with valid payload | G10: 200 | H10: PATCH /api/restaurant/regional | I10: Not Run | J10: ☐ | K10: ☐
A11: API-010 | B11: Restaurant | C11: GET Get service charges | D11: settings:access | E11: Auth = settings:access | F11: GET /api/restaurant/service-charges with valid payload | G11: 200 | H11: GET /api/restaurant/service-charges | I11: Not Run | J11: ☐ | K11: ☐
A12: API-011 | B12: Restaurant | C12: PATCH Patch POS/kiosk/online charges | D12: settings:edit | E12: Auth = settings:edit | F12: PATCH /api/restaurant/service-charges with valid payload | G12: 200 | H12: PATCH /api/restaurant/service-charges | I12: Not Run | J12: ☐ | K12: ☐
A13: API-012 | B13: Dashboard | C13: GET Dashboard analytics | D13: dashboard:access | E13: Auth = dashboard:access | F13: GET /api/restaurant/dashboard-analytics with valid payload | G13: 200 metrics | H13: GET /api/restaurant/dashboard-analytics | I13: Not Run | J13: ☐ | K13: ☐
... A202: API-NEG-10 | B202: Negatives | C202: Plan-denied recommendations POST | D202: STARTER | E202: — | F202: POST attributes | G202: 403 plan message | H202: subscriptionPlanDeniedResponse | I202: Not Run | J202: ☐ | K202: ☐

Sheet 06-UI
A1: ID | B1: Area | C1: Title | D1: Actor | E1: Preconditions | F1: Steps | G1: Expected | H1: White-box / API | I1: Result | J1: Approved | K1: Rejected | L1: Notes | M1: Tester | N1: Tested on
A2: UI-001-L | B2: Marketing | C2: Landing loads | D2: Guest | E2: Valid data/session | F2: Open / | G2: Renders; no blank crash; title/nav correct | H2: / | I2: Not Run | J2: ☐ | K2: ☐
A3: UI-002-L | B3: Marketing | C3: Pricing loads | D3: Guest | E3: Valid data/session | F3: Open /pricing | G3: Renders; no blank crash; title/nav correct | H3: /pricing | I3: Not Run | J3: ☐ | K3: ☐
A4: UI-003-L | B4: Marketing | C4: Blog list loads | D4: Guest | E4: Valid data/session | F4: Open /blog | G4: Renders; no blank crash; title/nav correct | H4: /blog | I4: Not Run | J4: ☐ | K4: ☐
A5: UI-004-L | B5: Marketing | C5: Blog post loads | D5: Guest | E5: Valid data/session | F5: Open /blog/[slug] | G5: Renders; no blank crash; title/nav correct | H5: /blog/[slug] | I5: Not Run | J5: ☐ | K5: ☐
A6: UI-005-L | B6: Marketing | C6: Docs home loads | D6: Guest | E6: Valid data/session | F6: Open /documentation | G6: Renders; no blank crash; title/nav correct | H6: /documentation | I6: Not Run | J6: ☐ | K6: ☐
A7: UI-006-L | B7: Marketing | C7: Docs article loads | D7: Guest | E7: Valid data/session | F7: Open /documentation/[heading]/[sub] | G7: Renders; no blank crash; title/nav correct | H7: /documentation/[heading]/[sub] | I7: Not Run | J7: ☐ | K7: ☐
A8: UI-007-L | B8: Marketing | C8: Demo request loads | D8: Guest | E8: Valid data/session | F8: Open /demo-request | G8: Renders; no blank crash; title/nav correct | H8: /demo-request | I8: Not Run | J8: ☐ | K8: ☐
A9: UI-008-L | B9: Marketing | C9: Privacy loads | D9: Guest | E9: Valid data/session | F9: Open /privacy | G9: Renders; no blank crash; title/nav correct | H9: /privacy | I9: Not Run | J9: ☐ | K9: ☐
A10: UI-009-L | B10: Marketing | C10: Privacy policy alias loads | D10: Guest | E10: Valid data/session | F10: Open /privacy-policy | G10: Renders; no blank crash; title/nav correct | H10: /privacy-policy | I10: Not Run | J10: ☐ | K10: ☐
A11: UI-010-L | B11: Marketing | C11: Refund policy loads | D11: Guest | E11: Valid data/session | F11: Open /refund-policy | G11: Renders; no blank crash; title/nav correct | H11: /refund-policy | I11: Not Run | J11: ☐ | K11: ☐
A12: UI-011-L | B12: Marketing | C12: Policies loads | D12: Guest | E12: Valid data/session | F12: Open /policies | G12: Renders; no blank crash; title/nav correct | H12: /policies | I12: Not Run | J12: ☐ | K12: ☐
A13: UI-012-L | B13: Marketing | C13: Subscription returns loads | D13: Guest | E13: Valid data/session | F13: Open /subscription-returns | G13: Renders; no blank crash; title/nav correct | H13: /subscription-returns | I13: Not Run | J13: ☐ | K13: ☐
... A109: UI-X-20 | B109: Cross UI | C109: Admin sidebar groups | D109: Platform admin | E109: — | F109: Open /admin | G109: Overview Management System groups | H109: ADMIN_NAV_GROUPS | I109: Not Run | J109: ☐ | K109: ☐

Sheet 07-Full-system
A1: ID | B1: Area | C1: Title | D1: Actor | E1: Preconditions | F1: Steps | G1: Expected | H1: White-box / API | I1: Result | J1: Approved | K1: Rejected | L1: Notes | M1: Tester | N1: Tested on
A2: E2E-01 | B2: Journey | C2: Owner signup → menu → POS cash → KDS → display → sales → stock | D2: Owner | E2: Fresh GROWTH | F2: Onboard; create category/product/recipe; POS sale; complete KDS; check sales+inventory | G2: All consistent; stock deducted; revenue counts | H2: multi-module | I2: Not Run | J2: ☐ | K2: ☐
A3: E2E-02 | B3: Journey | C3: Table dine-in full cycle | D3: Cashier | E3: Tables | F3: Open; send kitchen; add course; pay; complete KDS | G3: One order; table free; tickets closed | H3: table-orders | I3: Not Run | J3: ☐ | K3: ☐
A4: E2E-03 | B4: Journey | C4: Kiosk dine-in cash | D4: Guest+cashier | E4: Kiosk+POS | F4: Kiosk cash; POS pending cash; pay; KDS | G4: Paid kitchen ticket | H4: kiosk pending-cash | I4: Not Run | J4: ☐ | K4: ☐
A5: E2E-04 | B5: Journey | C5: Kiosk take-away card | D5: Guest | E5: Stripe/PayPal | F5: Pay on kiosk; success page; KDS | G5: Completed payment + ticket | H5: kiosk + payments | I5: Not Run | J5: ☐ | K5: ☐
A6: E2E-05 | B6: Journey | C6: Online delivery Stripe | D6: Guest | E6: Stripe | F6: Menu cart checkout pay webhook track | G6: Order ONLINE delivery; kitchen; track works | H6: customer/orders + stripe | I6: Not Run | J6: ☐ | K6: ☐
A7: E2E-06 | B7: Journey | C7: Online pickup JazzCash | D7: Guest | E7: WALLETS | F7: Pickup + JazzCash return | G7: Paid pickup order | H7: jazzcash return | I7: Not Run | J7: ☐ | K7: ☐
A8: E2E-07 | B8: Journey | C8: Online Easypaisa fail then retry | D8: Guest | E8: WALLETS | F8: Fail return; pay again | G8: One successful payment | H8: idempotency | I8: Not Run | J8: ☐ | K8: ☐
A9: E2E-08 | B9: Journey | C9: Logged-in customer reorder history | D9: Customer | E9: Prior paid order | F9: Login; orders; open detail | G9: Matches fulfillment snapshot | H9: me/orders | I9: Not Run | J9: ☐ | K9: ☐
A10: E2E-09 | B10: Journey | C10: Cashier RBAC cannot edit menu mid-shift | D10: Cashier | E10: pos+sales | F10: Sell; open /product | G10: Sale OK; product no-access | H10: RBAC | I10: Not Run | J10: ☐ | K10: ☐
A11: E2E-10 | B11: Journey | C11: Invite cashier → accept → POS only | D11: Owner+new user | E11: GROWTH | F11: Invite custom role; accept; login POS | G11: Only POS/sales modules | H11: invite + RBAC | I11: Not Run | J11: ☐ | K11: ☐
A12: E2E-11 | B12: Journey | C12: STARTER vs GROWTH feature split | D12: Two owners | E12: Both restaurants | F12: 2nd branch; logo; recommendation; analytics | G12: STARTER denied; GROWTH OK | H12: plan matrix | I12: Not Run | J12: ☐ | K12: ☐
A13: E2E-12 | B13: Journey | C13: Trial expires during open shift | D13: Owner | E13: Expire trial | F13: Use POS then dashboard | G13: Ops blocked per access rules; pricing redirect | H13: subscription-access | I13: Not Run | J13: ☐ | K13: ☐
... A26: E2E-25 | B26: Journey | C26: Platform admin changes plan; restaurant features change | D26: Admin+owner | E26: STARTER | F26: Admin PATCH to GROWTH; owner retry recs | G26: Recommendations unlock | H26: admin subscriptions | I26: Not Run | J26: ☐ | K26: ☐

Sheet Summary
A1: Test progress (formulas update as you mark Result)
A3: Metric | B3: 01-Modules | C3: 02-Functionality | D3: 03-RBAC | E3: 04-Security | F3: 05-API | G3: 06-UI | H3: 07-Full-system | I3: Total
A4: Total cases | B4: =COUNTA('01-Modules'!A2:A100) | C4: =COUNTA('02-Functionality'!A2:A88) | D4: =COUNTA('03-RBAC'!A2:A48) | E4: =COUNTA('04-Security'!A2:A33) | F4: =COUNTA('05-API'!A2:A202) | G4: =COUNTA('06-UI'!A2:A109) | H4: =COUNTA('07-Full-system'!A2:A26) | I4: =SUM(B4:H4)
A5: Not Run | B5: =COUNTIF('01-Modules'!I:I,"Not Run") | C5: =COUNTIF('02-Functionality'!I:I,"Not Run") | D5: =COUNTIF('03-RBAC'!I:I,"Not Run") | E5: =COUNTIF('04-Security'!I:I,"Not Run") | F5: =COUNTIF('05-API'!I:I,"Not Run") | G5: =COUNTIF('06-UI'!I:I,"Not Run") | H5: =COUNTIF('07-Full-system'!I:I,"Not Run") | I5: =SUM(B5:H5)
A6: Pass | B6: =COUNTIF('01-Modules'!I:I,"Pass") | C6: =COUNTIF('02-Functionality'!I:I,"Pass") | D6: =COUNTIF('03-RBAC'!I:I,"Pass") | E6: =COUNTIF('04-Security'!I:I,"Pass") | F6: =COUNTIF('05-API'!I:I,"Pass") | G6: =COUNTIF('06-UI'!I:I,"Pass") | H6: =COUNTIF('07-Full-system'!I:I,"Pass") | I6: =SUM(B6:H6)
A7: Fail | B7: =COUNTIF('01-Modules'!I:I,"Fail") | C7: =COUNTIF('02-Functionality'!I:I,"Fail") | D7: =COUNTIF('03-RBAC'!I:I,"Fail") | E7: =COUNTIF('04-Security'!I:I,"Fail") | F7: =COUNTIF('05-API'!I:I,"Fail") | G7: =COUNTIF('06-UI'!I:I,"Fail") | H7: =COUNTIF('07-Full-system'!I:I,"Fail") | I7: =SUM(B7:H7)
A8: Blocked | B8: =COUNTIF('01-Modules'!I:I,"Blocked") | C8: =COUNTIF('02-Functionality'!I:I,"Blocked") | D8: =COUNTIF('03-RBAC'!I:I,"Blocked") | E8: =COUNTIF('04-Security'!I:I,"Blocked") | F8: =COUNTIF('05-API'!I:I,"Blocked") | G8: =COUNTIF('06-UI'!I:I,"Blocked") | H8: =COUNTIF('07-Full-system'!I:I,"Blocked") | I8: =SUM(B8:H8)
A9: Approved ☑ | B9: =COUNTIF('01-Modules'!J:J,"☑") | C9: =COUNTIF('02-Functionality'!J:J,"☑") | D9: =COUNTIF('03-RBAC'!J:J,"☑") | E9: =COUNTIF('04-Security'!J:J,"☑") | F9: =COUNTIF('05-API'!J:J,"☑") | G9: =COUNTIF('06-UI'!J:J,"☑") | H9: =COUNTIF('07-Full-system'!J:J,"☑") | I9: =SUM(B9:H9)
A10: Rejected ☑ | B10: =COUNTIF('01-Modules'!K:K,"☑") | C10: =COUNTIF('02-Functionality'!K:K,"☑") | D10: =COUNTIF('03-RBAC'!K:K,"☑") | E10: =COUNTIF('04-Security'!K:K,"☑") | F10: =COUNTIF('05-API'!K:K,"☑") | G10: =COUNTIF('06-UI'!K:K,"☑") | H10: =COUNTIF('07-Full-system'!K:K,"☑") | I10: =SUM(B10:H10)
A13: Suggested order: Modules smoke → UI page loads → Functionality → API happy paths → RBAC → Security → Full system E2E.
